anomaly_grid_py-0.4.3.dist-info/METADATA
anomaly_grid_py-0.4.3.dist-info/WHEEL
anomaly_grid_py-0.4.3.dist-info/licenses/LICENSE
anomaly_grid_py/__init__.py
anomaly_grid_py/__init__.pyi
anomaly_grid_py/_core.pypy38-pp73-arm-linux-gnu.so
anomaly_grid_py/py.typed
anomaly_grid_py/utils.py
anomaly_grid_py-0.4.3.dist-info/RECORD
