Metadata-Version: 2.4
Name: anomaly-grid-py
Version: 0.4.3
Classifier: Development Status :: 4 - Beta
Classifier: Intended Audience :: Developers
Classifier: Intended Audience :: Science/Research
Classifier: License :: OSI Approved :: MIT License
Classifier: Operating System :: OS Independent
Classifier: Programming Language :: Python :: 3
Classifier: Programming Language :: Python :: 3.8
Classifier: Programming Language :: Python :: 3.9
Classifier: Programming Language :: Python :: 3.10
Classifier: Programming Language :: Python :: 3.11
Classifier: Programming Language :: Python :: 3.12
Classifier: Programming Language :: Rust
Classifier: Topic :: Scientific/Engineering :: Artificial Intelligence
Classifier: Topic :: Software Development :: Libraries :: Python Modules
Requires-Dist: numpy>=1.20.0
Requires-Dist: pytest>=6.0 ; extra == 'dev'
Requires-Dist: maturin>=1.0 ; extra == 'dev'
Requires-Dist: psutil ; extra == 'dev'
Requires-Dist: psutil ; extra == 'benchmarks'
Requires-Dist: matplotlib ; extra == 'benchmarks'
Requires-Dist: sphinx>=5.0 ; extra == 'docs'
Requires-Dist: sphinx-rtd-theme>=1.0 ; extra == 'docs'
Requires-Dist: myst-parser>=0.18 ; extra == 'docs'
Requires-Dist: pytest>=6.0 ; extra == 'test'
Requires-Dist: pytest-benchmark>=4.0 ; extra == 'test'
Provides-Extra: dev
Provides-Extra: benchmarks
Provides-Extra: docs
Provides-Extra: test
License-File: LICENSE
Summary: Deviation detection using variable-order Markov-chains in finite alphabet sequences
Keywords: anomaly-detection,sequence-analysis,markov-models,markov-chains,machine-learning
Author-email: Juan Abimael Santos Castillo <juanabimael@gmail.com>
License: MIT
Requires-Python: >=3.8
Project-URL: Homepage, https://github.com/abimael10/anomaly-grid-py
Project-URL: Repository, https://github.com/abimael10/anomaly-grid-py
Project-URL: Bug Tracker, https://github.com/abimael10/anomaly-grid-py/issues
